Workbook

Sheet Instructions
B1: EXAMPLE OF A FILLED UP FINANCIAL PLANNING & FORECASTING TEMPLATE
A5: Context
A8: • Two students start a small t-shirt company. It is an e-commerce firm, and sales happen online through its website. • The basic starting cost is the website design and development cost and the cost of office computers. We haven't considered a fixed deposit for office space since they'll be working out of college. The cost of a Chartered Accountant company registration is taken into account. • The basic working capital is INR 150,000 and the total startup investment is INR 550,000. Half of the amount is invested by founders and the other half is interest-free loan from college and friends and family. • The products being sold are only round neck t-shirts for now. These are printed with cool designs that are crowdsourced or designed by them. They keep rotating the design every 2-3 months.
A9: • COGS is INR 200. This includes t-shirt, printing, and packaging costs. The shipping cost is separate. • The selling price is at INR 400. The major expenses are online marketing costs, founder’s salary, and early employees' salaries, server costs, and shipping charges. • An extra inventory of 200 t-shirts is always bought in advance and held as a contingency from month four. • The founders work all by themselves till month six, then they start adding employees. The total employee count at the end of the year is 4. Not including the founders. • Break-even point is INR 2,60,000 per month. So, the students need to sell 650 t-shirts a month to break even. • The founders start paying the loan back in month 11.

Sheet 1. Startup Costs
A1: Starting costs
A3: Setting up the business
A4: Consultant Fees (Accountants, Lawyers etc.) | B4: 25000
A5: Business Registration fees | B5: 17000
A6: Website Design | B6: 0
A7: Website Development & Design | B7: 60000
A8: Computer Systems | B8: 0
A9: Other Start-Up Costs | B9: 30000
A10: Equipment
A11: Equipment | B11: NA
A12: Starting operations
A13: Marketing and Promotional Costs | B13: 50000
A14: Research | B14: 100000
A15: Stationery and office supplies | B15: 0
A16: Working capital | B16: 250000
A17: Start-up capital
A18: Equity investment (by Team) | B18: 300000
A19: Loans (from College or Others) | B19: 300000
A20: Total | B20: =SUM(B18:B19) -> 600000
A21: Totals
A22: Total set-up costs | B22: =SUM(B4:B16) -> 532000
A23: Surplus Funds | B23: =IF((B20-B22)>0,B20-B22,"0") -> 68000
A24: Additional Funds You Need | B24: =IF((B22-B20)>0,B22-B20,"0") -> 0

Sheet 2. Forecast P&L
A1: Profit and loss forecast
B3: =Instructions!D18 -> 0 | C3: =DATE(YEAR(B3),MONTH(B3)+1,DAY(B3)) -> 31 | D3: =DATE(YEAR(C3),MONTH(C3)+1,DAY(C3)) -> 62 | E3: =DATE(YEAR(D3),MONTH(D3)+1,DAY(D3)) -> 93 | F3: =DATE(YEAR(E3),MONTH(E3)+1,DAY(E3)) -> 123 | G3: =DATE(YEAR(F3),MONTH(F3)+1,DAY(F3)) -> 154 | H3: =DATE(YEAR(G3),MONTH(G3)+1,DAY(G3)) -> 184 | I3: =DATE(YEAR(H3),MONTH(H3)+1,DAY(H3)) -> 215 | J3: =DATE(YEAR(I3),MONTH(I3)+1,DAY(I3)) -> 246 | ... M3: =DATE(YEAR(L3),MONTH(L3)+1,DAY(L3)) -> 337 | N3: Totals
A4: Sales
A5: Cash Sales | B5: 382455 | C5: 382455 | D5: 382455 | E5: 849900 | F5: 849900 | G5: 849900 | H5: 849900 | I5: 1500000 | J5: 1500000 | K5: 1500000 | L5: 2400000 | M5: 2400000 | N5: =SUM(B5:M5) -> 13846965
A6: Collections from Accounts Receivable
A7: No. of Units Sold | B7: 45 | C7: 45 | D7: 45 | E7: 100 | F7: 100 | G7: 100 | H7: 100 | I7: 125 | J7: 125 | K7: 125 | L7: 200 | M7: 200
A8: Price Per Unit | B8: 8499 | C8: 8499 | D8: 8499 | E8: 8499 | F8: 8499 | G8: 8499 | H8: 8499 | I8: 12000 | J8: 12000 | K8: 12000 | L8: 12000 | M8: 12000
A9: Other Cash Receipts
A10: Total Sales | B10: =B5+B9+B6 -> 382455 | C10: =C5+C9+C6 -> 382455 | D10: =D5+D9+D6 -> 382455 | E10: =E5+E9+E6 -> 849900 | F10: =F5+F9+F6 -> 849900 | G10: =G5+G9+G6 -> 849900 | H10: =H5+H9+H6 -> 849900 | I10: =I5+I9+I6 -> 1500000 | ... M10: =M5+M9+M6 -> 2400000 | N10: =SUM(B10:M10) -> 13846965
A11: COGS
A12: Cost of Goods Sold | B12: 315000 | C12: 315000 | D12: 315000 | E12: 700000 | F12: 700000 | G12: 700000 | H12: 700000 | I12: 1125000 | J12: 1125000 | K12: 1125000 | L12: 1800000 | M12: 1800000 | N12: =SUM(B12:M12) -> 10720000
A13: Additional Inventories | N13: =SUM(B13:M13) -> 0
A14: Cost per unit | B14: 7000 | C14: 7000 | D14: 7000 | E14: 7000 | F14: 7000 | G14: 7000 | H14: 7000 | I14: 9000 | J14: 9000 | K14: 9000 | L14: 9000 | M14: 9000
A15: Gross profit | B15: =B5-B12-B13 -> 67455 | C15: =C5-C12-C13 -> 67455 | D15: =D5-D12-D13 -> 67455 | E15: =E5-E12-E13 -> 149900 | F15: =F5-F12-F13 -> 149900 | G15: =G5-G12-G13 -> 149900 | H15: =H5-H12-H13 -> 149900 | I15: =I5-I12-I13 -> 375000 | ... M15: =M5-M12-M13 -> 600000 | N15: =N5-N12+N13 -> 3126965
A16: Operating Expenses
A17: Salaries and Consultant Fees | B17: 0 | C17: 0 | D17: 0 | E17: 69000 | F17: 69000 | G17: 69000 | H17: 122000 | I17: 122000 | J17: 122000 | K17: 122000 | L17: 122000 | M17: 122000 | N17: =SUM(B17:M17) -> 939000
A18: Marketing and Promotion | B18: 2000 | C18: 2000 | D18: 2000 | E18: 5000 | F18: 5000 | G18: 5000 | H18: 5000 | I18: 5000 | J18: 10000 | K18: 10000 | L18: 10000 | M18: 10000 | N18: =SUM(B18:M18) -> 71000
A19: Trip Captain | B19: 21000 | C19: 21000 | D19: 21000 | E19: 35000 | F19: 35000 | G19: 35000 | H19: 35000 | I19: 60000 | J19: 60000 | K19: 60000 | L19: 96000 | M19: 96000 | N19: =SUM(B19:M19) -> 575000
A20: Office/Admin | B20: 0 | C20: 0 | D20: 0 | E20: 0 | F20: 0 | G20: 0 | H20: 10000 | I20: 10000 | J20: 10000 | K20: 10000 | L20: 10000 | M20: 10000 | N20: =SUM(B20:M20) -> 60000
A21: Volunteer Perks | B21: 21000 | C21: 21000 | D21: 21000 | E21: 35000 | F21: 35000 | G21: 35000 | H21: 35000 | I21: 120000 | J21: 120000 | K21: 120000 | L21: 192000 | M21: 192000 | N21: =SUM(B21:M21) -> 947000
A22: Misc. Expenses | B22: 5000 | C22: 5000 | D22: 5000 | E22: 5000 | F22: 5000 | G22: 5000 | H22: 10000 | I22: 10000 | J22: 10000 | K22: 10000 | L22: 10000 | M22: 10000 | N22: =SUM(B22:M22) -> 90000
A24: Total Expenses | B24: =SUM(B17:B22) -> 49000 | C24: =SUM(C17:C22) -> 49000 | D24: =SUM(D17:D22) -> 49000 | E24: =SUM(E17:E22) -> 149000 | F24: =SUM(F17:F22) -> 149000 | G24: =SUM(G17:G22) -> 149000 | H24: =SUM(H17:H22) -> 217000 | I24: =SUM(I17:I22) -> 327000 | ... M24: =SUM(M17:M22) -> 440000 | N24: =SUM(B24:M24) -> 2682000
A25: Result
A26: Net Profit/Loss | B26: =B15-B24 -> 18455 | C26: =C15-C24 -> 18455 | D26: =D15-D24 -> 18455 | E26: =E15-E24 -> 900 | F26: =F15-F24 -> 900 | G26: =G15-G24 -> 900 | H26: =H15-H24 -> -67100 | I26: =I15-I24 -> 48000 | ... N26: =N15-N24 -> 444965
A27: Gross Profit Margin | B27: =IF(ISERROR(B15/B5)," ",B15/B5) -> 0.17637369 | C27: =IF(ISERROR(C15/C5)," ",C15/C5) -> 0.17637369 | D27: =IF(ISERROR(D15/D5)," ",D15/D5) -> 0.17637369 | E27: =IF(ISERROR(E15/E5)," ",E15/E5) -> 0.17637369 | F27: =IF(ISERROR(F15/F5)," ",F15/F5) -> 0.17637369 | G27: =IF(ISERROR(G15/G5)," ",G15/G5) -> 0.17637369 | H27: =IF(ISERROR(H15/H5)," ",H15/H5) -> 0.17637369 | I27: =IF(ISERROR(I15/I5)," ",I15/I5) -> 0.25 | ... N27: =IF(ISERROR(N15/N5)," ",N15/N5) -> 0.22582313
A28: Net Profit Margin | B28: =IF(ISERROR(B26/B5)," ",B26/B5) -> 0.048254043 | C28: =IF(ISERROR(C26/C5)," ",C26/C5) -> 0.048254043 | D28: =IF(ISERROR(D26/D5)," ",D26/D5) -> 0.048254043 | E28: =IF(ISERROR(E26/E5)," ",E26/E5) -> 0.0010589481 | F28: =IF(ISERROR(F26/F5)," ",F26/F5) -> 0.0010589481 | G28: =IF(ISERROR(G26/G5)," ",G26/G5) -> 0.0010589481 | H28: =IF(ISERROR(H26/H5)," ",H26/H5) -> -0.078950465 | I28: =IF(ISERROR(I26/I5)," ",I26/I5) -> 0.032 | ... N28: =IF(ISERROR(N26/N5)," ",N26/N5) -> 0.032134479
K35: `

Sheet 3. Cash Flow
A1: Cash flow forecast
B3: =Instructions!D18 -> 0 | C3: =DATE(YEAR(B3),MONTH(B3)+1,DAY(B3)) -> 31 | D3: =DATE(YEAR(C3),MONTH(C3)+1,DAY(C3)) -> 62 | E3: =DATE(YEAR(D3),MONTH(D3)+1,DAY(D3)) -> 93 | F3: =DATE(YEAR(E3),MONTH(E3)+1,DAY(E3)) -> 123 | G3: =DATE(YEAR(F3),MONTH(F3)+1,DAY(F3)) -> 154 | H3: =DATE(YEAR(G3),MONTH(G3)+1,DAY(G3)) -> 184 | I3: =DATE(YEAR(H3),MONTH(H3)+1,DAY(H3)) -> 215 | J3: =DATE(YEAR(I3),MONTH(I3)+1,DAY(I3)) -> 246 | ... M3: =DATE(YEAR(L3),MONTH(L3)+1,DAY(L3)) -> 337 | N3: Totals
A4: Starting Cash Position | B4: 600000 | C4: 618455 | D4: =C16 -> 636910 | E4: =D16 -> 655365 | F4: =E16 -> 656265 | G4: =F16 -> 657165 | H4: =G16 -> 658065 | I4: =H16 -> 590965 | J4: =I16 -> 638965 | K4: =J16 -> 681965 | ... M4: =L16 -> 884965
A5: Cash Inflows
A6: Total Sales | B6: ='2. Forecast P&L'!B10 -> 382455 | C6: ='2. Forecast P&L'!C10 -> 382455 | D6: ='2. Forecast P&L'!D10 -> 382455 | E6: ='2. Forecast P&L'!E10 -> 849900 | F6: ='2. Forecast P&L'!F10 -> 849900 | G6: ='2. Forecast P&L'!G10 -> 849900 | H6: ='2. Forecast P&L'!H10 -> 849900 | I6: ='2. Forecast P&L'!I10 -> 1500000 | ... M6: ='2. Forecast P&L'!M10 -> 2400000 | N6: =B6+C6+D6+E6+F6+G6+H6+I6+J6+K6+L6+M6 -> 13846965
A7: Cash Outflows
A8: Cost Of Goods Sold | B8: ='2. Forecast P&L'!B12 -> 315000 | C8: ='2. Forecast P&L'!C12 -> 315000 | D8: ='2. Forecast P&L'!D12 -> 315000 | E8: ='2. Forecast P&L'!E12 -> 700000 | F8: ='2. Forecast P&L'!F12 -> 700000 | G8: ='2. Forecast P&L'!G12 -> 700000 | H8: ='2. Forecast P&L'!H12 -> 700000 | I8: ='2. Forecast P&L'!I12 -> 1125000 | ... M8: ='2. Forecast P&L'!M12 -> 1800000
A9: Operating Expenses | B9: ='2. Forecast P&L'!B24 -> 49000 | C9: ='2. Forecast P&L'!C24 -> 49000 | D9: ='2. Forecast P&L'!D24 -> 49000 | E9: ='2. Forecast P&L'!E24 -> 149000 | F9: ='2. Forecast P&L'!F24 -> 149000 | G9: ='2. Forecast P&L'!G24 -> 149000 | H9: ='2. Forecast P&L'!H24 -> 217000 | I9: ='2. Forecast P&L'!I24 -> 327000 | ... M9: ='2. Forecast P&L'!M24 -> 440000
A10: New Fixed Assets Purchased | B10: 0
A11: Additional Inventories Purchased
A12: Loan Payments | L12: 0 | M12: 0
A13: Total | B13: =SUM(B8:B12) -> 364000 | C13: =SUM(C8:C12) -> 364000 | D13: =SUM(D8:D12) -> 364000 | E13: =SUM(E8:E12) -> 849000 | F13: =SUM(F8:F12) -> 849000 | G13: =SUM(G8:G12) -> 849000 | H13: =SUM(H8:H12) -> 917000 | I13: =SUM(I8:I12) -> 1452000 | ... N13: =SUM(N8:N12) -> 0
A14: Result
A15: Change during month | B15: =IF(ISERR(B6-B13),"",(B6-B13)) -> 18455 | C15: =IF(ISERR(C6-C13),"",(C6-C13)) -> 18455 | D15: =IF(ISERR(D6-D13),"",(D6-D13)) -> 18455 | E15: =IF(ISERR(E6-E13),"",(E6-E13)) -> 900 | F15: =IF(ISERR(F6-F13),"",(F6-F13)) -> 900 | G15: =IF(ISERR(G6-G13),"",(G6-G13)) -> 900 | H15: =IF(ISERR(H6-H13),"",(H6-H13)) -> -67100 | I15: =IF(ISERR(I6-I13),"",(I6-I13)) -> 48000 | ... M15: =IF(ISERR(M6-M13),"",(M6-M13)) -> 160000
A16: Closing cash position | B16: =IF(ISERR(B4+B15),"",B4+B15) -> 618455 | C16: =IF(ISERR(C4+C15),"",C4+C15) -> 636910 | D16: =IF(ISERR(D4+D15),"",D4+D15) -> 655365 | E16: =IF(ISERR(E4+E15),"",E4+E15) -> 656265 | F16: =IF(ISERR(F4+F15),"",F4+F15) -> 657165 | G16: =IF(ISERR(G4+G15),"",G4+G15) -> 658065 | H16: =IF(ISERR(H4+H15),"",H4+H15) -> 590965 | I16: =IF(ISERR(I4+I15),"",I4+I15) -> 638965 | ... M16: =IF(ISERR(M4+M15),"",M4+M15) -> 1044965

Sheet 4. Balance Sheet
A1: Balance sheet forecast
A2: The numbers reflected on this Balance Sheet are computed as of:
A3: Assets
A4: Current assets
A5: Cash | B5: ='3. Cash Flow'!M16 -> 1044965
A6: Petty cash
A7: Accounts Receivable
A8: Stock on hand (Inventory) | B8: 20000
A9: Other Assets
A10: Fixed assets
A11: Equipment | B11: 50000
A12: Furniture
A13: Other Fixed Assets
A14: Total assets | B14: =SUM(B5:B13) -> 1114965
A15: Liabilities
A16: Current liabilities
A17: Accounts payable
A18: Interest payable
A19: Any Other Amounts Owed
A20: Long-term liabilities
A21: Loans from College | B21: ='1. Startup Costs'!B19-'3. Cash Flow'!L12-'3. Cash Flow'!M12 -> 300000
A22: Loans from Friends and Family
A23: Total liabilities | B23: =SUM(B16:B22) -> 300000
A24: Net assets | B24: =B14-B23 -> 814965
A25: Founder's equity
A26: Retained Earnings | B26: ='2. Forecast P&L'!N26 -> 444965
A27: Share Capital | B27: ='1. Startup Costs'!B18 -> 300000
A28: Total equity (should equal net assets) | B28: =SUM(B26:B27) -> 744965

Sheet 5. Break-Even Analysis
A1: Break-even analysis
A2: Average sales price per unit | B2: 9900
A3: Average cost of each unit | B3: 2120
A4: Gross Profit Margin | B4: =IF(ISERROR((B2-B3)/B2)," ",(B2-B3)/B2) -> 0.78585859
A5: Fixed costs | B5: ='2. Forecast P&L'!N24 -> 2682000
A6: Sales required to break even | B6: =IF(ISERROR(B5/B4), " ",B5/B4) -> 3412827.8
A7: Number of unit sales to break even | B7: =IF(ISERROR(B6/B2)," ",B6/B2) -> 344.73008
A10: Gross Margin % of Sales
A11: Gross Margin | B11: ='2. Forecast P&L'!N15 -> 3126965
A12: Total Sales | B12: ='2. Forecast P&L'!N10 -> 13846965
A13: Gross Margin/Total Sales | B13: =IF(B12>0, B11/B12, 0) -> 0.22582313
A14: Total Fixed Expenses
A15: Operating Expenses | B15: ='2. Forecast P&L'!N24 -> 2682000
A16: Breakeven Sales in Dollars (Annual)
A17: Gross Margin % of Sales | B17: =B13 -> 0.22582313
A18: Total Fixed Expenses | B18: ='2. Forecast P&L'!N24 -> 2682000
A19: Yearly Breakeven Amount | B19: =IF(B13=0,0,B15/ B13) -> 11876551
A20: Monthly Breakeven Amount | B20: =B19/12 -> 989712.61

Sheet 6. COGS Calculator
A1: Variable Costs of Products
A2: Timeframe: | B2: Month
A3: Product Line: | B3: Widget
A4: Transport | B4: 60000
A5: Food | B5: 17000
A6: Hotel/Homestay | B6: 40000
A7: Activities Cost | B7: 1000
A8: Team captain | B8: 3000
A9: Volunteer | B9: 7000
A10: Misc. | B10: 7000
A11: Cafe Booking for event | B11: 5000
A12: Total Product Expenses | B12: =SUM(B4:B11) -> 140000
A13: Number Units Sold During Timeframe
A14: Cost of Goods Sold (COGS) Per Unit | B14: 7000

Sheet 7. Salaries
A1: Salaries
B3: =Instructions!D18 -> 0 | C3: =DATE(YEAR(B3),MONTH(B3)+1,DAY(B3)) -> 31 | D3: =DATE(YEAR(C3),MONTH(C3)+1,DAY(C3)) -> 62 | E3: =DATE(YEAR(D3),MONTH(D3)+1,DAY(D3)) -> 93 | F3: =DATE(YEAR(E3),MONTH(E3)+1,DAY(E3)) -> 123 | G3: =DATE(YEAR(F3),MONTH(F3)+1,DAY(F3)) -> 154 | H3: =DATE(YEAR(G3),MONTH(G3)+1,DAY(G3)) -> 184 | I3: =DATE(YEAR(H3),MONTH(H3)+1,DAY(H3)) -> 215 | J3: =DATE(YEAR(I3),MONTH(I3)+1,DAY(I3)) -> 246 | ... M3: =DATE(YEAR(L3),MONTH(L3)+1,DAY(L3)) -> 337
A4: Employee Salaries
A5: Founder 1 (Siddhi) | B5: 0 | C5: 0 | D5: 0 | E5: 10000 | F5: 10000 | G5: 10000 | H5: 10000 | I5: 10000 | J5: 10000 | K5: 10000 | L5: 10000 | M5: 10000
A6: Founder 2 (Riya) | B6: 0 | C6: 0 | D6: 0 | E6: 10000 | F6: 10000 | G6: 10000 | H6: 10000 | I6: 10000 | J6: 10000 | K6: 10000 | L6: 10000 | M6: 10000
A7: Founder 3 (Chaitanya) | B7: 0 | C7: 0 | D7: 0 | E7: 10000 | F7: 10000 | G7: 10000 | H7: 10000 | I7: 10000 | J7: 10000 | K7: 10000 | L7: 12500 | M7: 12500
A8: Sales Executive | B8: 0 | C8: 0 | D8: 0 | E8: 0 | F8: 15000 | G8: 15000 | H8: 15000 | I8: 15000 | J8: 15000 | K8: 15000 | L8: 15000 | M8: 15000
A9: Social Media Manager | B9: 0 | C9: 0 | D9: 0 | E9: 0 | F9: 12000 | G9: 12000 | H9: 12000 | I9: 12000 | J9: 12000 | K9: 12000 | L9: 12000 | M9: 12000
A10: Website (Tech person) | B10: 0 | C10: 0 | D10: 0 | E10: 0 | F10: 0 | G10: 0 | H10: 20000 | I10: 20000 | J10: 20000 | K10: 20000 | L10: 20000 | M10: 20000
A11: Graphic designer | B11: 0 | C11: 0 | D11: 0 | E11: 0 | F11: 12000 | G11: 12000 | H11: 12000 | I11: 12000 | J11: 12000 | K11: 12000 | L11: 12000 | M11: 12000
A12: Team Captain | B12: 21000 | C12: 21000 | D12: 21000 | E12: 35000 | F12: 35000 | G12: 35000 | H12: 35000 | I12: 60000 | J12: 60000 | K12: 60000 | L12: 96000 | M12: 96000
A13: Operations Manager | B13: 0 | C13: 0 | D13: 0 | E13: 0 | F13: 0 | G13: 0 | H13: 15000 | I13: 15000 | J13: 15000 | K13: 15000 | L13: 15000 | M13: 15000
A14: Total Salaries | B14: =SUM(B5:B13) -> 21000 | C14: =SUM(C5:C13) -> 21000 | D14: =SUM(D5:D13) -> 21000 | E14: =SUM(E5:E13) -> 65000 | F14: =SUM(F5:F13) -> 104000 | G14: =SUM(G5:G13) -> 104000 | H14: =SUM(H5:H13) -> 139000 | I14: =SUM(I5:I13) -> 164000 | ... M14: =SUM(M5:M13) -> 202500
A15: Total Salaries | B15: =(B14+#REF!) -> #REF! | C15: =(C14+#REF!) -> #REF! | D15: =(D14+#REF!) -> #REF! | E15: =(E14+#REF!) -> #REF! | F15: =(F14+#REF!) -> #REF! | G15: =(G14+#REF!) -> #REF! | H15: =(H14+#REF!) -> #REF! | I15: =(I14+#REF!) -> #REF! | ... M15: =(M14+#REF!) -> #REF!
K22: `
